[
    {
        "streetId": 34,
        "headerPhoto": {
            "photoLocation": "img/str2/header-img.jpg",
            "ratio": 3.072
        },
        "streetName": "Avenue Ceramique",
        "cityName": "Maastricht",
        "verkeersintensiteit": 15000,
        "ruimte": 42,
        "identiteit": "img/str2/ident-icons.svg",
        "geojsonLine": {
            "type": "FeatureCollection",
            "features": [
                {
                    "type": "Feature",
                    "properties": {},
                    "geometry": {
                        "type": "LineString",
                        "coordinates": [
                            [
                                5.702872574329376,
                                50.842122925721824
                            ],
                            [
                                5.702421963214874,
                                50.84411468159361
                            ],
                            [
                                5.701968669891357,
                                50.846048771313455
                            ],
                            [
                                5.702000856399536,
                                50.846116513808255
                            ],
                            [
                                5.702075958251953,
                                50.846163933496065
                            ],
                            [
                                5.702207386493682,
                                50.84620965957797
                            ],
                            [
                                5.7023656368255615,
                                50.84624691783379
                            ],
                            [
                                5.702556073665618,
                                50.84628586961485
                            ],
                            [
                                5.702692866325378,
                                50.84634683755475
                            ],
                            [
                                5.702821612358093,
                                50.84641627316702
                            ],
                            [
                                5.702961087226868,
                                50.846522966711284
                            ],
                            [
                                5.703084468841553,
                                50.84664490189165
                            ],
                            [
                                5.7031649351119995,
                                50.84677022382827
                            ],
                            [
                                5.703205168247223,
                                50.84693280313626
                            ],
                            [
                                5.703186392784119,
                                50.8470733660396
                            ],
                            [
                                5.703138113021851,
                                50.84719021921518
                            ]
                        ]
                    }
                }
            ]
        },
        "geojsonFog": {
            "type": "FeatureCollection",
            "features": [
                {
                    "type": "Feature",
                    "properties": {},
                    "geometry": {
                        "type": "Point",
                        "coordinates": [
                            5.703105926513672,
                            50.84722239612516
                        ]
                    }
                },
                {
                    "type": "Feature",
                    "properties": {},
                    "geometry": {
                        "type": "Point",
                        "coordinates": [
                            5.703207850456238,
                            50.8470174796348
                        ]
                    }
                },
                {
                    "type": "Feature",
                    "properties": {},
                    "geometry": {
                        "type": "Point",
                        "coordinates": [
                            5.703213214874268,
                            50.846800707491674
                        ]
                    }
                },
                {
                    "type": "Feature",
                    "properties": {},
                    "geometry": {
                        "type": "Point",
                        "coordinates": [
                            5.703105926513672,
                            50.8465907085175
                        ]
                    }
                },
                {
                    "type": "Feature",
                    "properties": {},
                    "geometry": {
                        "type": "Point",
                        "coordinates": [
                            5.702907443046569,
                            50.846417966717226
                        ]
                    }
                },
                {
                    "type": "Feature",
                    "properties": {},
                    "geometry": {
                        "type": "Point",
                        "coordinates": [
                            5.702349543571472,
                            50.846204578904405
                        ]
                    }
                },
                {
                    "type": "Feature",
                    "properties": {},
                    "geometry": {
                        "type": "Point",
                        "coordinates": [
                            5.7020920515060425,
                            50.84615715925789
                        ]
                    }
                },
                {
                    "type": "Feature",
                    "properties": {},
                    "geometry": {
                        "type": "Point",
                        "coordinates": [
                            5.701995491981506,
                            50.84599796437783
                        ]
                    }
                },
                {
                    "type": "Feature",
                    "properties": {},
                    "geometry": {
                        "type": "Point",
                        "coordinates": [
                            5.70202499628067,
                            50.84573884814537
                        ]
                    }
                },
                {
                    "type": "Feature",
                    "properties": {},
                    "geometry": {
                        "type": "Point",
                        "coordinates": [
                            5.702110826969147,
                            50.84543061650446
                        ]
                    }
                },
                {
                    "type": "Feature",
                    "properties": {},
                    "geometry": {
                        "type": "Point",
                        "coordinates": [
                            5.702172517776489,
                            50.8451901266671
                        ]
                    }
                },
                {
                    "type": "Feature",
                    "properties": {},
                    "geometry": {
                        "type": "Point",
                        "coordinates": [
                            5.702236890792847,
                            50.84486664894475
                        ]
                    }
                },
                {
                    "type": "Feature",
                    "properties": {},
                    "geometry": {
                        "type": "Point",
                        "coordinates": [
                            5.702419281005859,
                            50.84414516699222
                        ]
                    }
                },
                {
                    "type": "Feature",
                    "properties": {},
                    "geometry": {
                        "type": "Point",
                        "coordinates": [
                            5.702470242977142,
                            50.843896202320764
                        ]
                    }
                },
                {
                    "type": "Feature",
                    "properties": {},
                    "geometry": {
                        "type": "Point",
                        "coordinates": [
                            5.7025399804115295,
                            50.84359134581165
                        ]
                    }
                },
                {
                    "type": "Feature",
                    "properties": {},
                    "geometry": {
                        "type": "Point",
                        "coordinates": [
                            5.70265531539917,
                            50.84306800415952
                        ]
                    }
                },
                {
                    "type": "Feature",
                    "properties": {},
                    "geometry": {
                        "type": "Point",
                        "coordinates": [
                            5.702741146087646,
                            50.84268862013314
                        ]
                    }
                },
                {
                    "type": "Feature",
                    "properties": {},
                    "geometry": {
                        "type": "Point",
                        "coordinates": [
                            5.70278137922287,
                            50.84247182787588
                        ]
                    }
                },
                {
                    "type": "Feature",
                    "properties": {},
                    "geometry": {
                        "type": "Point",
                        "coordinates": [
                            5.702872574329376,
                            50.842124619427906
                        ]
                    }
                },
                {
                    "type": "Feature",
                    "properties": {},
                    "geometry": {
                        "type": "Point",
                        "coordinates": [
                            5.702569484710693,
                            50.84337286408815
                        ]
                    }
                },
                {
                    "type": "Feature",
                    "properties": {},
                    "geometry": {
                        "type": "Point",
                        "coordinates": [
                            5.702719688415527,
                            50.84283088950452
                        ]
                    }
                },
                {
                    "type": "Feature",
                    "properties": {},
                    "geometry": {
                        "type": "Point",
                        "coordinates": [
                            5.702333450317383,
                            50.844524539175076
                        ]
                    }
                },
                {
                    "type": "Feature",
                    "properties": {},
                    "geometry": {
                        "type": "Point",
                        "coordinates": [
                            5.702671408653259,
                            50.84630619227035
                        ]
                    }
                },
                {
                    "type": "Feature",
                    "properties": {},
                    "geometry": {
                        "type": "Point",
                        "coordinates": [
                            5.703154206275939,
                            50.84691417428595
                        ]
                    }
                },
                {
                    "type": "Feature",
                    "properties": {},
                    "geometry": {
                        "type": "Point",
                        "coordinates": [
                            5.703068375587463,
                            50.84669740166282
                        ]
                    }
                },
                {
                    "type": "Feature",
                    "properties": {},
                    "geometry": {
                        "type": "Point",
                        "coordinates": [
                            5.702936947345734,
                            50.84655175699094
                        ]
                    }
                },
                {
                    "type": "Feature",
                    "properties": {},
                    "geometry": {
                        "type": "Point",
                        "coordinates": [
                            5.702741146087646,
                            50.846412886066354
                        ]
                    }
                },
                {
                    "type": "Feature",
                    "properties": {},
                    "geometry": {
                        "type": "Point",
                        "coordinates": [
                            5.702505111694336,
                            50.8462892567247
                        ]
                    }
                }
            ]
        },
        "mapCity": {
            "center": [
                5.702184,
                50.844943
            ],
            "pitch": 0,
            "bearing": 0,
            "zoom": 13
        },
        "mapStreet": {
            "center": [
                5.702184,
                50.8447
            ],
            "pitch": 0,
            "bearing": 0,
            "zoom": 14.7
        },
        "streetCrossSectionPng": "img/str2/Doorsnedes.png",
        "expertJudgement": {
            "gender": "female",
            "photoLocation": "",
            "judgementText": "Dit vind ik een van de mooiste straten in Maastricht. De verkeersfunctie is nog vrij fors, maar door het scheiden van de rijrichtingen blijft de weg nog goed oversteek-baar. Hij oogt naar mijn mening wat duister door de vele bomen en de hoge bebouwing erlangs. De vele bomen zorgen er echter ook voor dat het zicht over het verkeer minder wordt. Daarnaast zou het mooi zijn als de aparte busbaan weg zou kunnen, waardoor er meer ruimte komt voor het overige verkeer.",
            "expertName": "Viviane de Groot",
            "expertDescription": "Verkeerskundig ontwerper bij gemeente Maastricht"
        },
        "functionalAmbiance": "img/str2/funtionalAmbiance.svg",
        "photos": [
            {
                "fileLocation": "img/str2/1.jpg",
                "textDescription": "Middenberm van haag zorgt voor een statig beeld"
            },
            {
                "fileLocation": "img/str2/2.jpg",
                "textDescription": "Zebrapaden"
            },
            {
                "fileLocation": "img/str2/3.jpg",
                "textDescription": "Brede parkeerstrook"
            },
            {
                "fileLocation": "img/str2/4.jpg",
                "textDescription": "Oversteekbaarheid alleen mogelijk op aangewezen plekken"
            },
            {
                "fileLocation": "img/str2/5.jpg",
                "textDescription": "Voldoende opstelruimte voor auto"
            },
            {
                "fileLocation": "img/str2/6.jpg",
                "textDescription": "Binnenpleinen langs de weg"
            },
            {
                "fileLocation": "img/str2/7.jpg",
                "textDescription": "Veel bomen aanwezig"
            }
        ]
    },
    {
        "streetId": 0,
        "headerPhoto": {
            "photoLocation": "img/str3/header-img.jpg",
            "ratio": 3.072
        },
        "streetName": "Zandweg",
        "cityName": "Utrecht",
        "verkeersintensiteit": 500,
        "ruimte": 17.5,
        "identiteit": "img/str3/ident-icons.svg",
        "geojsonLine": {
            "type": "FeatureCollection",
            "features": [
              {
                "type": "Feature",
                "properties": {},
                "geometry": {
                  "type": "LineString",
                  "coordinates": [
                    [
                      4.9941471219062805,
                      52.09047474608058
                    ],
                    [
                      4.994342923164368,
                      52.09046485812065
                    ],
                    [
                      4.994758665561676,
                      52.09040553031507
                    ],
                    [
                      4.995903968811035,
                      52.09019953037766
                    ],
                    [
                      4.998009502887726,
                      52.0898221360251
                    ],
                    [
                      5.000434219837189,
                      52.089406833747255
                    ],
                    [
                      5.002199113368988,
                      52.08909865059026
                    ],
                    [
                      5.003172755241393,
                      52.08893714198949
                    ],
                    [
                      5.0043636560440055,
                      52.08872783915759
                    ],
                    [
                      5.0058066844940186,
                      52.08847238948913
                    ],
                    [
                      5.006463825702667,
                      52.08835702464341
                    ],
                    [
                      5.007941722869872,
                      52.08807849971509
                    ],
                    [
                      5.008982419967651,
                      52.08788732183504
                    ],
                    [
                      5.01037985086441,
                      52.08763021925669
                    ],
                    [
                      5.012166202068329,
                      52.08730719084051
                    ],
                    [
                      5.014360249042511,
                      52.086939660768124
                    ],
                    [
                      5.01724898815155,
                      52.08643698020733
                    ],
                    [
                      5.018233358860016,
                      52.086268869379246
                    ],
                    [
                      5.019300878047943,
                      52.086161739599596
                    ],
                    [
                      5.019713938236237,
                      52.08608922083354
                    ],
                    [
                      5.020030438899994,
                      52.08603153536732
                    ],
                    [
                      5.0205883383750916,
                      52.0858897936193
                    ],
                    [
                      5.021859705448151,
                      52.08567223564188
                    ],
                    [
                      5.021945536136627,
                      52.0856623466177
                    ],
                    [
                      5.022157430648804,
                      52.08568212466387
                    ],
                    [
                      5.022245943546294,
                      52.08567058747134
                    ],
                    [
                      5.022715330123901,
                      52.08556840077874
                    ],
                    [
                      5.022798478603363,
                      52.08552225187316
                    ],
                    [
                      5.02288430929184,
                      52.08547939927521
                    ],
                    [
                      5.0230103731155396,
                      52.08545467660383
                    ],
                    [
                      5.0235119462013245,
                      52.08535084123453
                    ],
                    [
                      5.024378299713135,
                      52.085187670880295
                    ],
                    [
                      5.025810599327087,
                      52.084927256351854
                    ],
                    [
                      5.026835203170776,
                      52.084752547019
                    ],
                    [
                      5.028278231620789,
                      52.08450037102122
                    ],
                    [
                      5.029758810997009,
                      52.08423665603523
                    ],
                    [
                      5.030893385410309,
                      52.084045461695965
                    ],
                    [
                      5.031394958496094,
                      52.0839894218206
                    ],
                    [
                      5.0315505266189575,
                      52.083964698323825
                    ],
                    [
                      5.031816065311432,
                      52.08387899009556
                    ],
                    [
                      5.032129883766174,
                      52.083818005294475
                    ],
                    [
                      5.032465159893036,
                      52.08375042744455
                    ],
                    [
                      5.032931864261626,
                      52.08367296002731
                    ],
                    [
                      5.033554136753082,
                      52.08356087927075
                    ],
                    [
                      5.034635066986084,
                      52.08337792331341
                    ],
                    [
                      5.035407543182373,
                      52.08325595225852
                    ],
                    [
                      5.036657452583313,
                      52.08304167797651
                    ],
                    [
                      5.03697395324707,
                      52.08298893338008
                    ],
                    [
                      5.037459433078766,
                      52.08290816809599
                    ],
                    [
                      5.037891268730164,
                      52.08283564404289
                    ],
                    [
                      5.038462579250335,
                      52.08273674741691
                    ],
                    [
                      5.039283335208892,
                      52.0825966434883
                    ],
                    [
                      5.039878785610198,
                      52.082486208316965
                    ],
                    [
                      5.040699541568756,
                      52.082339510428014
                    ],
                    [
                      5.041501522064209,
                      52.08219940525242
                    ],
                    [
                      5.042161345481872,
                      52.08209061740099
                    ],
                    [
                      5.042754113674164,
                      52.08198347759117
                    ],
                    [
                      5.043279826641083,
                      52.08188952400784
                    ],
                    [
                      5.043505132198334,
                      52.081849964545164
                    ],
                    [
                      5.0437331199646,
                      52.08185161285679
                    ],
                    [
                      5.044197142124176,
                      52.081876337524186
                    ],
                    [
                      5.045774281024933,
                      52.08197029113527
                    ],
                    [
                      5.047702789306641,
                      52.08206094794093
                    ],
                    [
                      5.049338936805725,
                      52.08209556230907
                    ],
                    [
                      5.05118429660797,
                      52.08214830796129
                    ],
                    [
                      5.052780210971832,
                      52.08227357863544
                    ],
                    [
                      5.054408311843872,
                      52.08241533186902
                    ],
                    [
                      5.055658221244812,
                      52.08250433948324
                    ],
                    [
                      5.05645751953125,
                      52.0825307120756
                    ],
                    [
                      5.058190226554871,
                      52.0825406017937
                    ],
                    [
                      5.0597083568573,
                      52.082570270934916
                    ],
                    [
                      5.0608402490615845,
                      52.082553788081135
                    ],
                    [
                      5.062106251716614,
                      52.0825406017937
                    ],
                    [
                      5.063517093658447,
                      52.082505987770745
                    ],
                    [
                      5.06470263004303,
                      52.082517525781384
                    ],
                    [
                      5.06542682647705,
                      52.08253895350752
                    ],
                    [
                      5.066354870796204,
                      52.082537305221265
                    ],
                    [
                      5.067274868488312,
                      52.0825307120756
                    ],
                    [
                      5.06832093000412,
                      52.0824779668753
                    ],
                    [
                      5.068597197532654,
                      52.08244829767277
                    ],
                    [
                      5.068913698196411,
                      52.08241862845049
                    ],
                    [
                      5.069157779216766,
                      52.08239720066657
                    ],
                    [
                      5.069219470024109,
                      52.082374124580106
                    ],
                    [
                      5.0692301988601685,
                      52.082299951364156
                    ],
                    [
                      5.069270431995391,
                      52.082240612702655
                    ]
                  ]
                }
              }
            ]
          },
        "geojsonFog": {
            "type": "FeatureCollection",
            "features": [
              {
                "type": "Feature",
                "properties": {},
                "geometry": {
                  "type": "Point",
                  "coordinates": [
                    4.99416321516037,
                    52.09047804206673
                  ]
                }
              },
              {
                "type": "Feature",
                "properties": {},
                "geometry": {
                  "type": "Point",
                  "coordinates": [
                    4.994369745254517,
                    52.090463210127126
                  ]
                }
              },
              {
                "type": "Feature",
                "properties": {},
                "geometry": {
                  "type": "Point",
                  "coordinates": [
                    4.9945467710494995,
                    52.090440138211235
                  ]
                }
              },
              {
                "type": "Feature",
                "properties": {},
                "geometry": {
                  "type": "Point",
                  "coordinates": [
                    4.994753301143646,
                    52.090417066283436
                  ]
                }
              },
              {
                "type": "Feature",
                "properties": {},
                "geometry": {
                  "type": "Point",
                  "coordinates": [
                    4.994916915893555,
                    52.090382458369376
                  ]
                }
              },
              {
                "type": "Feature",
                "properties": {},
                "geometry": {
                  "type": "Point",
                  "coordinates": [
                    4.995091259479523,
                    52.09035114642399
                  ]
                }
              },
              {
                "type": "Feature",
                "properties": {},
                "geometry": {
                  "type": "Point",
                  "coordinates": [
                    4.99526023864746,
                    52.09031818645773
                  ]
                }
              },
              {
                "type": "Feature",
                "properties": {},
                "geometry": {
                  "type": "Point",
                  "coordinates": [
                    4.9954211711883545,
                    52.09029181846722
                  ]
                }
              },
              {
                "type": "Feature",
                "properties": {},
                "geometry": {
                  "type": "Point",
                  "coordinates": [
                    4.995563328266144,
                    52.090268746462705
                  ]
                }
              },
              {
                "type": "Feature",
                "properties": {},
                "geometry": {
                  "type": "Point",
                  "coordinates": [
                    4.995898604393005,
                    52.09020117838092
                  ]
                }
              },
              {
                "type": "Feature",
                "properties": {},
                "geometry": {
                  "type": "Point",
                  "coordinates": [
                    4.996239244937897,
                    52.09014185022475
                  ]
                }
              },
              {
                "type": "Feature",
                "properties": {},
                "geometry": {
                  "type": "Point",
                  "coordinates": [
                    4.996579885482788,
                    52.09007592995868
                  ]
                }
              },
              {
                "type": "Feature",
                "properties": {},
                "geometry": {
                  "type": "Point",
                  "coordinates": [
                    4.996941983699799,
                    52.090016601635966
                  ]
                }
              },
              {
                "type": "Feature",
                "properties": {},
                "geometry": {
                  "type": "Point",
                  "coordinates": [
                    4.997247755527496,
                    52.089957273234354
                  ]
                }
              },
              {
                "type": "Feature",
                "properties": {},
                "geometry": {
                  "type": "Point",
                  "coordinates": [
                    4.9979183077812195,
                    52.0898353201611
                  ]
                }
              },
              {
                "type": "Feature",
                "properties": {},
                "geometry": {
                  "type": "Point",
                  "coordinates": [
                    4.99853253364563,
                    52.089724902901864
                  ]
                }
              },
              {
                "type": "Feature",
                "properties": {},
                "geometry": {
                  "type": "Point",
                  "coordinates": [
                    4.999186992645264,
                    52.08963261363972
                  ]
                }
              },
              {
                "type": "Feature",
                "properties": {},
                "geometry": {
                  "type": "Point",
                  "coordinates": [
                    4.999750256538391,
                    52.08952549193537
                  ]
                }
              },
              {
                "type": "Feature",
                "properties": {},
                "geometry": {
                  "type": "Point",
                  "coordinates": [
                    5.000292062759399,
                    52.089424962101994
                  ]
                }
              },
              {
                "type": "Feature",
                "properties": {},
                "geometry": {
                  "type": "Point",
                  "coordinates": [
                    5.000772178173065,
                    52.08934256043028
                  ]
                }
              },
              {
                "type": "Feature",
                "properties": {},
                "geometry": {
                  "type": "Point",
                  "coordinates": [
                    5.001244246959686,
                    52.0892634546823
                  ]
                }
              },
              {
                "type": "Feature",
                "properties": {},
                "geometry": {
                  "type": "Point",
                  "coordinates": [
                    5.001673400402068,
                    52.08918434879408
                  ]
                }
              },
              {
                "type": "Feature",
                "properties": {},
                "geometry": {
                  "type": "Point",
                  "coordinates": [
                    5.0021883845329285,
                    52.089092058413904
                  ]
                }
              },
              {
                "type": "Feature",
                "properties": {},
                "geometry": {
                  "type": "Point",
                  "coordinates": [
                    5.002665817737579,
                    52.089012952221815
                  ]
                }
              },
              {
                "type": "Feature",
                "properties": {},
                "geometry": {
                  "type": "Point",
                  "coordinates": [
                    5.0030896067619315,
                    52.088940438089196
                  ]
                }
              },
              {
                "type": "Feature",
                "properties": {},
                "geometry": {
                  "type": "Point",
                  "coordinates": [
                    5.003416836261749,
                    52.08888770046421
                  ]
                }
              },
              {
                "type": "Feature",
                "properties": {},
                "geometry": {
                  "type": "Point",
                  "coordinates": [
                    5.00377357006073,
                    52.08881518612806
                  ]
                }
              },
              {
                "type": "Feature",
                "properties": {},
                "geometry": {
                  "type": "Point",
                  "coordinates": [
                    5.004130303859711,
                    52.08875750418559
                  ]
                }
              },
              {
                "type": "Feature",
                "properties": {},
                "geometry": {
                  "type": "Point",
                  "coordinates": [
                    5.004465579986572,
                    52.08870311828585
                  ]
                }
              },
              {
                "type": "Feature",
                "properties": {},
                "geometry": {
                  "type": "Point",
                  "coordinates": [
                    5.004800856113434,
                    52.08863884395522
                  ]
                }
              },
              {
                "type": "Feature",
                "properties": {},
                "geometry": {
                  "type": "Point",
                  "coordinates": [
                    5.005103945732116,
                    52.08859764241252
                  ]
                }
              },
              {
                "type": "Feature",
                "properties": {},
                "geometry": {
                  "type": "Point",
                  "coordinates": [
                    5.0054070353508,
                    52.08854820051107
                  ]
                }
              },
              {
                "type": "Feature",
                "properties": {},
                "geometry": {
                  "type": "Point",
                  "coordinates": [
                    5.00577449798584,
                    52.0884839259573
                  ]
                }
              },
              {
                "type": "Feature",
                "properties": {},
                "geometry": {
                  "type": "Point",
                  "coordinates": [
                    5.006171464920044,
                    52.08841305903427
                  ]
                }
              },
              {
                "type": "Feature",
                "properties": {},
                "geometry": {
                  "type": "Point",
                  "coordinates": [
                    5.0065577030181885,
                    52.08833559971063
                  ]
                }
              },
              {
                "type": "Feature",
                "properties": {},
                "geometry": {
                  "type": "Point",
                  "coordinates": [
                    5.006890296936035,
                    52.08827132485063
                  ]
                }
              },
              {
                "type": "Feature",
                "properties": {},
                "geometry": {
                  "type": "Point",
                  "coordinates": [
                    5.007338225841522,
                    52.08818892104851
                  ]
                }
              },
              {
                "type": "Feature",
                "properties": {},
                "geometry": {
                  "type": "Point",
                  "coordinates": [
                    5.007829070091248,
                    52.08809168436628
                  ]
                }
              },
              {
                "type": "Feature",
                "properties": {},
                "geometry": {
                  "type": "Point",
                  "coordinates": [
                    5.0083038210868835,
                    52.08801587256872
                  ]
                }
              },
              {
                "type": "Feature",
                "properties": {},
                "geometry": {
                  "type": "Point",
                  "coordinates": [
                    5.008700788021087,
                    52.08793511638186
                  ]
                }
              },
              {
                "type": "Feature",
                "properties": {},
                "geometry": {
                  "type": "Point",
                  "coordinates": [
                    5.009113848209381,
                    52.08785930431829
                  ]
                }
              },
              {
                "type": "Feature",
                "properties": {},
                "geometry": {
                  "type": "Point",
                  "coordinates": [
                    5.009588599205017,
                    52.0877719554767
                  ]
                }
              },
              {
                "type": "Feature",
                "properties": {},
                "geometry": {
                  "type": "Point",
                  "coordinates": [
                    5.009993612766266,
                    52.08770108742298
                  ]
                }
              },
              {
                "type": "Feature",
                "properties": {},
                "geometry": {
                  "type": "Point",
                  "coordinates": [
                    5.0105032324790955,
                    52.087600553479255
                  ]
                }
              },
              {
                "type": "Feature",
                "properties": {},
                "geometry": {
                  "type": "Point",
                  "coordinates": [
                    5.0109270215034485,
                    52.087531333255185
                  ]
                }
              },
              {
                "type": "Feature",
                "properties": {},
                "geometry": {
                  "type": "Point",
                  "coordinates": [
                    5.011294484138489,
                    52.08745387240096
                  ]
                }
              },
              {
                "type": "Feature",
                "properties": {},
                "geometry": {
                  "type": "Point",
                  "coordinates": [
                    5.011696815490723,
                    52.087384651949364
                  ]
                }
              },
              {
                "type": "Feature",
                "properties": {},
                "geometry": {
                  "type": "Point",
                  "coordinates": [
                    5.012029409408569,
                    52.08733520870391
                  ]
                }
              },
              {
                "type": "Feature",
                "properties": {},
                "geometry": {
                  "type": "Point",
                  "coordinates": [
                    5.012372732162476,
                    52.08727422862572
                  ]
                }
              },
              {
                "type": "Feature",
                "properties": {},
                "geometry": {
                  "type": "Point",
                  "coordinates": [
                    5.012670457363129,
                    52.08721819280478
                  ]
                }
              },
              {
                "type": "Feature",
                "properties": {},
                "geometry": {
                  "type": "Point",
                  "coordinates": [
                    5.012992322444916,
                    52.087158860682344
                  ]
                }
              },
              {
                "type": "Feature",
                "properties": {},
                "geometry": {
                  "type": "Point",
                  "coordinates": [
                    5.013308823108673,
                    52.0871094171867
                  ]
                }
              },
              {
                "type": "Feature",
                "properties": {},
                "geometry": {
                  "type": "Point",
                  "coordinates": [
                    5.013657510280609,
                    52.08705173303924
                  ]
                }
              },
              {
                "type": "Feature",
                "properties": {},
                "geometry": {
                  "type": "Point",
                  "coordinates": [
                    5.014051795005798,
                    52.08698745632994
                  ]
                }
              },
              {
                "type": "Feature",
                "properties": {},
                "geometry": {
                  "type": "Point",
                  "coordinates": [
                    5.014454126358032,
                    52.08691164265638
                  ]
                }
              },
              {
                "type": "Feature",
                "properties": {},
                "geometry": {
                  "type": "Point",
                  "coordinates": [
                    5.014853775501251,
                    52.086858902633594
                  ]
                }
              },
              {
                "type": "Feature",
                "properties": {},
                "geometry": {
                  "type": "Point",
                  "coordinates": [
                    5.015301704406738,
                    52.08676990370379
                  ]
                }
              },
              {
                "type": "Feature",
                "properties": {},
                "geometry": {
                  "type": "Point",
                  "coordinates": [
                    5.015760362148285,
                    52.08669573779337
                  ]
                }
              },
              {
                "type": "Feature",
                "properties": {},
                "geometry": {
                  "type": "Point",
                  "coordinates": [
                    5.016178786754608,
                    52.0866232198951
                  ]
                }
              },
              {
                "type": "Feature",
                "properties": {},
                "geometry": {
                  "type": "Point",
                  "coordinates": [
                    5.01649796962738,
                    52.08657212766874
                  ]
                }
              },
              {
                "type": "Feature",
                "properties": {},
                "geometry": {
                  "type": "Point",
                  "coordinates": [
                    5.016873478889465,
                    52.08651444282675
                  ]
                }
              },
              {
                "type": "Feature",
                "properties": {},
                "geometry": {
                  "type": "Point",
                  "coordinates": [
                    5.0172194838523865,
                    52.086440276491736
                  ]
                }
              },
              {
                "type": "Feature",
                "properties": {},
                "geometry": {
                  "type": "Point",
                  "coordinates": [
                    5.017584264278412,
                    52.08638259147929
                  ]
                }
              },
              {
                "type": "Feature",
                "properties": {},
                "geometry": {
                  "type": "Point",
                  "coordinates": [
                    5.017973184585571,
                    52.08631831380618
                  ]
                }
              },
              {
                "type": "Feature",
                "properties": {},
                "geometry": {
                  "type": "Point",
                  "coordinates": [
                    5.018335282802582,
                    52.0862523878914
                  ]
                }
              },
              {
                "type": "Feature",
                "properties": {},
                "geometry": {
                  "type": "Point",
                  "coordinates": [
                    5.018689334392547,
                    52.08621448044633
                  ]
                }
              },
              {
                "type": "Feature",
                "properties": {},
                "geometry": {
                  "type": "Point",
                  "coordinates": [
                    5.019062161445618,
                    52.086174924817115
                  ]
                }
              },
              {
                "type": "Feature",
                "properties": {},
                "geometry": {
                  "type": "Point",
                  "coordinates": [
                    5.0193920731544495,
                    52.08614031361279
                  ]
                }
              },
              {
                "type": "Feature",
                "properties": {},
                "geometry": {
                  "type": "Point",
                  "coordinates": [
                    5.019735395908356,
                    52.08608922083354
                  ]
                }
              },
              {
                "type": "Feature",
                "properties": {},
                "geometry": {
                  "type": "Point",
                  "coordinates": [
                    5.020078718662262,
                    52.08601340563395
                  ]
                }
              },
              {
                "type": "Feature",
                "properties": {},
                "geometry": {
                  "type": "Point",
                  "coordinates": [
                    5.020456910133361,
                    52.085922756856675
                  ]
                }
              },
              {
                "type": "Feature",
                "properties": {},
                "geometry": {
                  "type": "Point",
                  "coordinates": [
                    5.020896792411804,
                    52.08583375605986
                  ]
                }
              },
              {
                "type": "Feature",
                "properties": {},
                "geometry": {
                  "type": "Point",
                  "coordinates": [
                    5.021293759346008,
                    52.085769477596216
                  ]
                }
              },
              {
                "type": "Feature",
                "properties": {},
                "geometry": {
                  "type": "Point",
                  "coordinates": [
                    5.021741688251495,
                    52.085683772833995
                  ]
                }
              },
              {
                "type": "Feature",
                "properties": {},
                "geometry": {
                  "type": "Point",
                  "coordinates": [
                    5.022149384021759,
                    52.085683772833995
                  ]
                }
              },
              {
                "type": "Feature",
                "properties": {},
                "geometry": {
                  "type": "Point",
                  "coordinates": [
                    5.0226858258247375,
                    52.085570048953066
                  ]
                }
              },
              {
                "type": "Feature",
                "properties": {},
                "geometry": {
                  "type": "Point",
                  "coordinates": [
                    5.023007690906525,
                    52.0854381948153
                  ]
                }
              },
              {
                "type": "Feature",
                "properties": {},
                "geometry": {
                  "type": "Point",
                  "coordinates": [
                    5.023463666439056,
                    52.08535413759916
                  ]
                }
              },
              {
                "type": "Feature",
                "properties": {},
                "geometry": {
                  "type": "Point",
                  "coordinates": [
                    5.023833811283112,
                    52.08527832115075
                  ]
                }
              },
              {
                "type": "Feature",
                "properties": {},
                "geometry": {
                  "type": "Point",
                  "coordinates": [
                    5.024187862873077,
                    52.08521569007447
                  ]
                }
              },
              {
                "type": "Feature",
                "properties": {},
                "geometry": {
                  "type": "Point",
                  "coordinates": [
                    5.024603605270386,
                    52.08514646615106
                  ]
                }
              },
              {
                "type": "Feature",
                "properties": {},
                "geometry": {
                  "type": "Point",
                  "coordinates": [
                    5.024971067905426,
                    52.08507559392773
                  ]
                }
              },
              {
                "type": "Feature",
                "properties": {},
                "geometry": {
                  "type": "Point",
                  "coordinates": [
                    5.0253599882125854,
                    52.08501296256695
                  ]
                }
              },
              {
                "type": "Feature",
                "properties": {},
                "geometry": {
                  "type": "Point",
                  "coordinates": [
                    5.02575159072876,
                    52.08494209013162
                  ]
                }
              },
              {
                "type": "Feature",
                "properties": {},
                "geometry": {
                  "type": "Point",
                  "coordinates": [
                    5.0261190533638,
                    52.08487451398382
                  ]
                }
              },
              {
                "type": "Feature",
                "properties": {},
                "geometry": {
                  "type": "Point",
                  "coordinates": [
                    5.0265079736709595,
                    52.08480693773369
                  ]
                }
              },
              {
                "type": "Feature",
                "properties": {},
                "geometry": {
                  "type": "Point",
                  "coordinates": [
                    5.026886165142059,
                    52.08473771317623
                  ]
                }
              },
              {
                "type": "Feature",
                "properties": {},
                "geometry": {
                  "type": "Point",
                  "coordinates": [
                    5.027229487895966,
                    52.08467837775582
                  ]
                }
              },
              {
                "type": "Feature",
                "properties": {},
                "geometry": {
                  "type": "Point",
                  "coordinates": [
                    5.0275808572769165,
                    52.08463552434757
                  ]
                }
              },
              {
                "type": "Feature",
                "properties": {},
                "geometry": {
                  "type": "Point",
                  "coordinates": [
                    5.027918815612792,
                    52.084563003101394
                  ]
                }
              },
              {
                "type": "Feature",
                "properties": {},
                "geometry": {
                  "type": "Point",
                  "coordinates": [
                    5.028294324874878,
                    52.08449212995148
                  ]
                }
              },
              {
                "type": "Feature",
                "properties": {},
                "geometry": {
                  "type": "Point",
                  "coordinates": [
                    5.028672516345978,
                    52.084422904905715
                  ]
                }
              },
              {
                "type": "Feature",
                "properties": {},
                "geometry": {
                  "type": "Point",
                  "coordinates": [
                    5.029056072235107,
                    52.08435862440995
                  ]
                }
              },
              {
                "type": "Feature",
                "properties": {},
                "geometry": {
                  "type": "Point",
                  "coordinates": [
                    5.029461085796356,
                    52.084284454492064
                  ]
                }
              },
              {
                "type": "Feature",
                "properties": {},
                "geometry": {
                  "type": "Point",
                  "coordinates": [
                    5.0297293066978455,
                    52.0842300631406
                  ]
                }
              },
              {
                "type": "Feature",
                "properties": {},
                "geometry": {
                  "type": "Point",
                  "coordinates": [
                    5.03011554479599,
                    52.08416743059319
                  ]
                }
              },
              {
                "type": "Feature",
                "properties": {},
                "geometry": {
                  "type": "Point",
                  "coordinates": [
                    5.030434727668762,
                    52.084121280238854
                  ]
                }
              },
              {
                "type": "Feature",
                "properties": {},
                "geometry": {
                  "type": "Point",
                  "coordinates": [
                    5.03073513507843,
                    52.084078426295655
                  ]
                }
              },
              {
                "type": "Feature",
                "properties": {},
                "geometry": {
                  "type": "Point",
                  "coordinates": [
                    5.030984580516815,
                    52.084037220542236
                  ]
                }
              },
              {
                "type": "Feature",
                "properties": {},
                "geometry": {
                  "type": "Point",
                  "coordinates": [
                    5.031368136405945,
                    52.0839894218206
                  ]
                }
              },
              {
                "type": "Feature",
                "properties": {},
                "geometry": {
                  "type": "Point",
                  "coordinates": [
                    5.031706094741821,
                    52.08390206540398
                  ]
                }
              },
              {
                "type": "Feature",
                "properties": {},
                "geometry": {
                  "type": "Point",
                  "coordinates": [
                    5.032038688659668,
                    52.083829542965944
                  ]
                }
              },
              {
                "type": "Feature",
                "properties": {},
                "geometry": {
                  "type": "Point",
                  "coordinates": [
                    5.0323498249053955,
                    52.0837619651335
                  ]
                }
              },
              {
                "type": "Feature",
                "properties": {},
                "geometry": {
                  "type": "Point",
                  "coordinates": [
                    5.032679736614227,
                    52.08370922138831
                  ]
                }
              },
              {
                "type": "Feature",
                "properties": {},
                "geometry": {
                  "type": "Point",
                  "coordinates": [
                    5.033020377159119,
                    52.08365318109074
                  ]
                }
              },
              {
                "type": "Feature",
                "properties": {},
                "geometry": {
                  "type": "Point",
                  "coordinates": [
                    5.033339560031891,
                    52.08360208546398
                  ]
                }
              },
              {
                "type": "Feature",
                "properties": {},
                "geometry": {
                  "type": "Point",
                  "coordinates": [
                    5.033637285232544,
                    52.083544396782834
                  ]
                }
              },
              {
                "type": "Feature",
                "properties": {},
                "geometry": {
                  "type": "Point",
                  "coordinates": [
                    5.0339484214782715,
                    52.083493301031524
                  ]
                }
              },
              {
                "type": "Feature",
                "properties": {},
                "geometry": {
                  "type": "Point",
                  "coordinates": [
                    5.034259557723999,
                    52.083440556968846
                  ]
                }
              },
              {
                "type": "Feature",
                "properties": {},
                "geometry": {
                  "type": "Point",
                  "coordinates": [
                    5.034543871879578,
                    52.08339275760817
                  ]
                }
              },
              {
                "type": "Feature",
                "properties": {},
                "geometry": {
                  "type": "Point",
                  "coordinates": [
                    5.034849643707275,
                    52.08334166168328
                  ]
                }
              },
              {
                "type": "Feature",
                "properties": {},
                "geometry": {
                  "type": "Point",
                  "coordinates": [
                    5.035152733325957,
                    52.08329715873327
                  ]
                }
              },
              {
                "type": "Feature",
                "properties": {},
                "geometry": {
                  "type": "Point",
                  "coordinates": [
                    5.03547728061676,
                    52.083236173137124
                  ]
                }
              },
              {
                "type": "Feature",
                "properties": {},
                "geometry": {
                  "type": "Point",
                  "coordinates": [
                    5.035858154296875,
                    52.083170242669155
                  ]
                }
              },
              {
                "type": "Feature",
                "properties": {},
                "geometry": {
                  "type": "Point",
                  "coordinates": [
                    5.036257803440094,
                    52.08310760863439
                  ]
                }
              },
              {
                "type": "Feature",
                "properties": {},
                "geometry": {
                  "type": "Point",
                  "coordinates": [
                    5.036536753177643,
                    52.08305980891711
                  ]
                }
              },
              {
                "type": "Feature",
                "properties": {},
                "geometry": {
                  "type": "Point",
                  "coordinates": [
                    5.03684788942337,
                    52.08301036087989
                  ]
                }
              },
              {
                "type": "Feature",
                "properties": {},
                "geometry": {
                  "type": "Point",
                  "coordinates": [
                    5.037164390087128,
                    52.082957616246446
                  ]
                }
              },
              {
                "type": "Feature",
                "properties": {},
                "geometry": {
                  "type": "Point",
                  "coordinates": [
                    5.037507712841034,
                    52.08289827845932
                  ]
                }
              },
              {
                "type": "Feature",
                "properties": {},
                "geometry": {
                  "type": "Point",
                  "coordinates": [
                    5.0377920269966125,
                    52.08285707161629
                  ]
                }
              },
              {
                "type": "Feature",
                "properties": {},
                "geometry": {
                  "type": "Point",
                  "coordinates": [
                    5.038087069988251,
                    52.08280597507811
                  ]
                }
              },
              {
                "type": "Feature",
                "properties": {},
                "geometry": {
                  "type": "Point",
                  "coordinates": [
                    5.03835529088974,
                    52.08275487848141
                  ]
                }
              },
              {
                "type": "Feature",
                "properties": {},
                "geometry": {
                  "type": "Point",
                  "coordinates": [
                    5.038661062717438,
                    52.08269389214427
                  ]
                }
              },
              {
                "type": "Feature",
                "properties": {},
                "geometry": {
                  "type": "Point",
                  "coordinates": [
                    5.03896951675415,
                    52.08263620228919
                  ]
                }
              },
              {
                "type": "Feature",
                "properties": {},
                "geometry": {
                  "type": "Point",
                  "coordinates": [
                    5.039310157299042,
                    52.082575215789866
                  ]
                }
              },
              {
                "type": "Feature",
                "properties": {},
                "geometry": {
                  "type": "Point",
                  "coordinates": [
                    5.039626657962799,
                    52.082517525781384
                  ]
                }
              },
              {
                "type": "Feature",
                "properties": {},
                "geometry": {
                  "type": "Point",
                  "coordinates": [
                    5.039919018745422,
                    52.08246642885444
                  ]
                }
              },
              {
                "type": "Feature",
                "properties": {},
                "geometry": {
                  "type": "Point",
                  "coordinates": [
                    5.040200650691986,
                    52.08242357332224
                  ]
                }
              },
              {
                "type": "Feature",
                "properties": {},
                "geometry": {
                  "type": "Point",
                  "coordinates": [
                    5.040511786937714,
                    52.08235928994677
                  ]
                }
              },
              {
                "type": "Feature",
                "properties": {},
                "geometry": {
                  "type": "Point",
                  "coordinates": [
                    5.040844380855559,
                    52.082298303069074
                  ]
                }
              },
              {
                "type": "Feature",
                "properties": {},
                "geometry": {
                  "type": "Point",
                  "coordinates": [
                    5.041136741638184,
                    52.0822587439687
                  ]
                }
              },
              {
                "type": "Feature",
                "properties": {},
                "geometry": {
                  "type": "Point",
                  "coordinates": [
                    5.041437149047852,
                    52.08220764674551
                  ]
                }
              },
              {
                "type": "Feature",
                "properties": {},
                "geometry": {
                  "type": "Point",
                  "coordinates": [
                    5.0417643785476685,
                    52.08214830796129
                  ]
                }
              },
              {
                "type": "Feature",
                "properties": {},
                "geometry": {
                  "type": "Point",
                  "coordinates": [
                    5.042134523391724,
                    52.082092265703764
                  ]
                }
              },
              {
                "type": "Feature",
                "properties": {},
                "geometry": {
                  "type": "Point",
                  "coordinates": [
                    5.042448341846465,
                    52.08203457507102
                  ]
                }
              },
              {
                "type": "Feature",
                "properties": {},
                "geometry": {
                  "type": "Point",
                  "coordinates": [
                    5.0427621603012085,
                    52.08197193944247
                  ]
                }
              },
              {
                "type": "Feature",
                "properties": {},
                "geometry": {
                  "type": "Point",
                  "coordinates": [
                    5.0431618094444275,
                    52.08191095203547
                  ]
                }
              },
              {
                "type": "Feature",
                "properties": {},
                "geometry": {
                  "type": "Point",
                  "coordinates": [
                    5.043540000915527,
                    52.08184337129798
                  ]
                }
              },
              {
                "type": "Feature",
                "properties": {},
                "geometry": {
                  "type": "Point",
                  "coordinates": [
                    5.0440362095832825,
                    52.08186315103661
                  ]
                }
              },
              {
                "type": "Feature",
                "properties": {},
                "geometry": {
                  "type": "Point",
                  "coordinates": [
                    5.044489502906799,
                    52.081896117248206
                  ]
                }
              },
              {
                "type": "Feature",
                "properties": {},
                "geometry": {
                  "type": "Point",
                  "coordinates": [
                    5.044891834259033,
                    52.08191589696347
                  ]
                }
              },
              {
                "type": "Feature",
                "properties": {},
                "geometry": {
                  "type": "Point",
                  "coordinates": [
                    5.045221745967865,
                    52.08194886313611
                  ]
                }
              },
              {
                "type": "Feature",
                "properties": {},
                "geometry": {
                  "type": "Point",
                  "coordinates": [
                    5.0456830859184265,
                    52.08196864282802
                  ]
                }
              },
              {
                "type": "Feature",
                "properties": {},
                "geometry": {
                  "type": "Point",
                  "coordinates": [
                    5.045999586582184,
                    52.08198018097757
                  ]
                }
              },
              {
                "type": "Feature",
                "properties": {},
                "geometry": {
                  "type": "Point",
                  "coordinates": [
                    5.04633754491806,
                    52.08200490557371
                  ]
                }
              },
              {
                "type": "Feature",
                "properties": {},
                "geometry": {
                  "type": "Point",
                  "coordinates": [
                    5.046683549880981,
                    52.082019740324824
                  ]
                }
              },
              {
                "type": "Feature",
                "properties": {},
                "geometry": {
                  "type": "Point",
                  "coordinates": [
                    5.04697322845459,
                    52.08203127846118
                  ]
                }
              },
              {
                "type": "Feature",
                "properties": {},
                "geometry": {
                  "type": "Point",
                  "coordinates": [
                    5.047292411327362,
                    52.082037871680605
                  ]
                }
              },
              {
                "type": "Feature",
                "properties": {},
                "geometry": {
                  "type": "Point",
                  "coordinates": [
                    5.04760354757309,
                    52.082051058116534
                  ]
                }
              },
              {
                "type": "Feature",
                "properties": {},
                "geometry": {
                  "type": "Point",
                  "coordinates": [
                    5.047909319400787,
                    52.082062596244796
                  ]
                }
              },
              {
                "type": "Feature",
                "properties": {},
                "geometry": {
                  "type": "Point",
                  "coordinates": [
                    5.04822850227356,
                    52.08207907928
                  ]
                }
              },
              {
                "type": "Feature",
                "properties": {},
                "geometry": {
                  "type": "Point",
                  "coordinates": [
                    5.048582553863525,
                    52.08207413437006
                  ]
                }
              },
              {
                "type": "Feature",
                "properties": {},
                "geometry": {
                  "type": "Point",
                  "coordinates": [
                    5.048885643482208,
                    52.082077430976746
                  ]
                }
              },
              {
                "type": "Feature",
                "properties": {},
                "geometry": {
                  "type": "Point",
                  "coordinates": [
                    5.049237012863159,
                    52.08207907928
                  ]
                }
              },
              {
                "type": "Feature",
                "properties": {},
                "geometry": {
                  "type": "Point",
                  "coordinates": [
                    5.04958301782608,
                    52.082092265703764
                  ]
                }
              },
              {
                "type": "Feature",
                "properties": {},
                "geometry": {
                  "type": "Point",
                  "coordinates": [
                    5.049942433834076,
                    52.08211039703008
                  ]
                }
              },
              {
                "type": "Feature",
                "properties": {},
                "geometry": {
                  "type": "Point",
                  "coordinates": [
                    5.050291121006012,
                    52.08211039703008
                  ]
                }
              },
              {
                "type": "Feature",
                "properties": {},
                "geometry": {
                  "type": "Point",
                  "coordinates": [
                    5.050618350505829,
                    52.0821169902378
                  ]
                }
              },
              {
                "type": "Feature",
                "properties": {},
                "geometry": {
                  "type": "Point",
                  "coordinates": [
                    5.050934851169586,
                    52.082140066457235
                  ]
                }
              },
              {
                "type": "Feature",
                "properties": {},
                "geometry": {
                  "type": "Point",
                  "coordinates": [
                    5.051264762878417,
                    52.082151604562476
                  ]
                }
              },
              {
                "type": "Feature",
                "properties": {},
                "geometry": {
                  "type": "Point",
                  "coordinates": [
                    5.051610767841339,
                    52.08216808756478
                  ]
                }
              },
              {
                "type": "Feature",
                "properties": {},
                "geometry": {
                  "type": "Point",
                  "coordinates": [
                    5.051943361759185,
                    52.08219281205686
                  ]
                }
              },
              {
                "type": "Feature",
                "properties": {},
                "geometry": {
                  "type": "Point",
                  "coordinates": [
                    5.052289366722107,
                    52.08222412972712
                  ]
                }
              },
              {
                "type": "Feature",
                "properties": {},
                "geometry": {
                  "type": "Point",
                  "coordinates": [
                    5.052635371685028,
                    52.082255447375424
                  ]
                }
              },
              {
                "type": "Feature",
                "properties": {},
                "geometry": {
                  "type": "Point",
                  "coordinates": [
                    5.052930414676665,
                    52.082278523523264
                  ]
                }
              },
              {
                "type": "Feature",
                "properties": {},
                "geometry": {
                  "type": "Point",
                  "coordinates": [
                    5.053265690803528,
                    52.08230324795415
                  ]
                }
              },
              {
                "type": "Feature",
                "properties": {},
                "geometry": {
                  "type": "Point",
                  "coordinates": [
                    5.053627789020538,
                    52.08233456554693
                  ]
                }
              },
              {
                "type": "Feature",
                "properties": {},
                "geometry": {
                  "type": "Point",
                  "coordinates": [
                    5.05395233631134,
                    52.082370827995355
                  ]
                }
              },
              {
                "type": "Feature",
                "properties": {},
                "geometry": {
                  "type": "Point",
                  "coordinates": [
                    5.05432516336441,
                    52.082398848958015
                  ]
                }
              },
              {
                "type": "Feature",
                "properties": {},
                "geometry": {
                  "type": "Point",
                  "coordinates": [
                    5.054636299610137,
                    52.082430166483725
                  ]
                }
              },
              {
                "type": "Feature",
                "properties": {},
                "geometry": {
                  "type": "Point",
                  "coordinates": [
                    5.055001080036163,
                    52.08246148398745
                  ]
                }
              },
              {
                "type": "Feature",
                "properties": {},
                "geometry": {
                  "type": "Point",
                  "coordinates": [
                    5.05534440279007,
                    52.08248456002875
                  ]
                }
              },
              {
                "type": "Feature",
                "properties": {},
                "geometry": {
                  "type": "Point",
                  "coordinates": [
                    5.05570650100708,
                    52.08250433948324
                  ]
                }
              },
              {
                "type": "Feature",
                "properties": {},
                "geometry": {
                  "type": "Point",
                  "coordinates": [
                    5.056052505970001,
                    52.08251422920721
                  ]
                }
              },
              {
                "type": "Feature",
                "properties": {},
                "geometry": {
                  "type": "Point",
                  "coordinates": [
                    5.056433379650116,
                    52.08252082235529
                  ]
                }
              },
              {
                "type": "Feature",
                "properties": {},
                "geometry": {
                  "type": "Point",
                  "coordinates": [
                    5.056749880313873,
                    52.08253236036209
                  ]
                }
              },
              {
                "type": "Feature",
                "properties": {},
                "geometry": {
                  "type": "Point",
                  "coordinates": [
                    5.05708783864975,
                    52.08253400864855
                  ]
                }
              },
              {
                "type": "Feature",
                "properties": {},
                "geometry": {
                  "type": "Point",
                  "coordinates": [
                    5.057452619075774,
                    52.0825406017937
                  ]
                }
              },
              {
                "type": "Feature",
                "properties": {},
                "geometry": {
                  "type": "Point",
                  "coordinates": [
                    5.0577932596206665,
                    52.08254884322381
                  ]
                }
              },
              {
                "type": "Feature",
                "properties": {},
                "geometry": {
                  "type": "Point",
                  "coordinates": [
                    5.058123171329498,
                    52.082550491509636
                  ]
                }
              },
              {
                "type": "Feature",
                "properties": {},
                "geometry": {
                  "type": "Point",
                  "coordinates": [
                    5.058482587337494,
                    52.08254884322381
                  ]
                }
              },
              {
                "type": "Feature",
                "properties": {},
                "geometry": {
                  "type": "Point",
                  "coordinates": [
                    5.058745443820953,
                    52.08255213979541
                  ]
                }
              },
              {
                "type": "Feature",
                "properties": {},
                "geometry": {
                  "type": "Point",
                  "coordinates": [
                    5.05908876657486,
                    52.08255708465237
                  ]
                }
              },
              {
                "type": "Feature",
                "properties": {},
                "geometry": {
                  "type": "Point",
                  "coordinates": [
                    5.05942404270172,
                    52.08255873293792
                  ]
                }
              },
              {
                "type": "Feature",
                "properties": {},
                "geometry": {
                  "type": "Point",
                  "coordinates": [
                    5.059778094291687,
                    52.082555436366775
                  ]
                }
              },
              {
                "type": "Feature",
                "properties": {},
                "geometry": {
                  "type": "Point",
                  "coordinates": [
                    5.0600892305374146,
                    52.082543898365934
                  ]
                }
              },
              {
                "type": "Feature",
                "properties": {},
                "geometry": {
                  "type": "Point",
                  "coordinates": [
                    5.060411095619201,
                    52.08255213979541
                  ]
                }
              },
              {
                "type": "Feature",
                "properties": {},
                "geometry": {
                  "type": "Point",
                  "coordinates": [
                    5.060743689537048,
                    52.082545546651936
                  ]
                }
              },
              {
                "type": "Feature",
                "properties": {},
                "geometry": {
                  "type": "Point",
                  "coordinates": [
                    5.0610655546188354,
                    52.082545546651936
                  ]
                }
              },
              {
                "type": "Feature",
                "properties": {},
                "geometry": {
                  "type": "Point",
                  "coordinates": [
                    5.061344504356384,
                    52.082545546651936
                  ]
                }
              },
              {
                "type": "Feature",
                "properties": {},
                "geometry": {
                  "type": "Point",
                  "coordinates": [
                    5.061669051647186,
                    52.08253236036209
                  ]
                }
              },
              {
                "type": "Feature",
                "properties": {},
                "geometry": {
                  "type": "Point",
                  "coordinates": [
                    5.062025785446167,
                    52.082543898365934
                  ]
                }
              },
              {
                "type": "Feature",
                "properties": {},
                "geometry": {
                  "type": "Point",
                  "coordinates": [
                    5.06233423948288,
                    52.08253236036209
                  ]
                }
              },
              {
                "type": "Feature",
                "properties": {},
                "geometry": {
                  "type": "Point",
                  "coordinates": [
                    5.062682926654816,
                    52.082517525781384
                  ]
                }
              },
              {
                "type": "Feature",
                "properties": {},
                "geometry": {
                  "type": "Point",
                  "coordinates": [
                    5.0630369782447815,
                    52.082512580920046
                  ]
                }
              },
              {
                "type": "Feature",
                "properties": {},
                "geometry": {
                  "type": "Point",
                  "coordinates": [
                    5.0633615255355835,
                    52.082499394620456
                  ]
                }
              },
              {
                "type": "Feature",
                "properties": {},
                "geometry": {
                  "type": "Point",
                  "coordinates": [
                    5.063715577125549,
                    52.082505987770745
                  ]
                }
              },
              {
                "type": "Feature",
                "properties": {},
                "geometry": {
                  "type": "Point",
                  "coordinates": [
                    5.064037442207336,
                    52.082512580920046
                  ]
                }
              },
              {
                "type": "Feature",
                "properties": {},
                "geometry": {
                  "type": "Point",
                  "coordinates": [
                    5.064375400543213,
                    52.082499394620456
                  ]
                }
              },
              {
                "type": "Feature",
                "properties": {},
                "geometry": {
                  "type": "Point",
                  "coordinates": [
                    5.064732134342194,
                    52.08250433948324
                  ]
                }
              },
              {
                "type": "Feature",
                "properties": {},
                "geometry": {
                  "type": "Point",
                  "coordinates": [
                    5.065094232559204,
                    52.08252411892898
                  ]
                }
              },
              {
                "type": "Feature",
                "properties": {},
                "geometry": {
                  "type": "Point",
                  "coordinates": [
                    5.065375864505768,
                    52.08253565693496
                  ]
                }
              },
              {
                "type": "Feature",
                "properties": {},
                "geometry": {
                  "type": "Point",
                  "coordinates": [
                    5.065727233886719,
                    52.082529063789046
                  ]
                }
              },
              {
                "type": "Feature",
                "properties": {},
                "geometry": {
                  "type": "Point",
                  "coordinates": [
                    5.066011548042297,
                    52.0825307120756
                  ]
                }
              },
              {
                "type": "Feature",
                "properties": {},
                "geometry": {
                  "type": "Point",
                  "coordinates": [
                    5.066293179988861,
                    52.08252576721572
                  ]
                }
              },
              {
                "type": "Feature",
                "properties": {},
                "geometry": {
                  "type": "Point",
                  "coordinates": [
                    5.066625773906708,
                    52.08252247064216
                  ]
                }
              },
              {
                "type": "Feature",
                "properties": {},
                "geometry": {
                  "type": "Point",
                  "coordinates": [
                    5.0669825077056885,
                    52.08252741550243
                  ]
                }
              },
              {
                "type": "Feature",
                "properties": {},
                "geometry": {
                  "type": "Point",
                  "coordinates": [
                    5.06732851266861,
                    52.08253236036209
                  ]
                }
              },
              {
                "type": "Feature",
                "properties": {},
                "geometry": {
                  "type": "Point",
                  "coordinates": [
                    5.06769597530365,
                    52.08251422920721
                  ]
                }
              },
              {
                "type": "Feature",
                "properties": {},
                "geometry": {
                  "type": "Point",
                  "coordinates": [
                    5.068033933639526,
                    52.082499394620456
                  ]
                }
              },
              {
                "type": "Feature",
                "properties": {},
                "geometry": {
                  "type": "Point",
                  "coordinates": [
                    5.068377256393433,
                    52.0824779668753
                  ]
                }
              },
              {
                "type": "Feature",
                "properties": {},
                "geometry": {
                  "type": "Point",
                  "coordinates": [
                    5.068733990192413,
                    52.08244500109349
                  ]
                }
              },
              {
                "type": "Feature",
                "properties": {},
                "geometry": {
                  "type": "Point",
                  "coordinates": [
                    5.069018304347992,
                    52.08241038699634
                  ]
                }
              },
              {
                "type": "Feature",
                "properties": {},
                "geometry": {
                  "type": "Point",
                  "coordinates": [
                    5.069265067577362,
                    52.08224555759412
                  ]
                }
              },
              {
                "type": "Feature",
                "properties": {},
                "geometry": {
                  "type": "Point",
                  "coordinates": [
                    5.069222152233124,
                    52.08236753141032
                  ]
                }
              }
            ]
          },
        "mapCity": {
            "center":  [
                5.05,
                52.08
              ],
            "pitch": 0,
            "bearing": 0,
            "zoom": 10
        },
        "mapStreet": {
            "center":  [
                5.03293,
                52.0836
              ],
            "pitch": 0,
            "bearing": 0,
            "zoom": 12.5
        },
        "streetCrossSectionPng": "img/str3/Doorsnedes.png",
        "expertJudgement": {
            "gender": "",
            "photoLocation": "img/str3/marco.jpg",
            "judgementText": "Samen met de gemeente en met bewoners, ondernemers en belanghebbenden hebben we een ontwerp gemaakt voor de Zandweg in Utrecht. Het is 1 van de top5             doorfietsroutes van de stad Utrecht en de langste fietsstraat van Nederland. We hebben een belans gezocht tussen woonkwaliteit, parkeren, de water- en de bomenstructuur, auto, voetganger en fiets. Het parkeren gebeurde in de oude situatie op de straat en op de stoep. Om meer ruimte aan de voetganger te geven, is de stoep verbreed. Het parkeren vindt incidenteel plaats op groene parkeerplaatsen in de berm op een eco plus rooster. De fietser kan zo prettig doorfietsen.",
            "expertName": "Marco Aarsen",
            "expertDescription": "Landschapsarchitect en Adviseur, Goudappel Coffeng"
        },
        "functionalAmbiance": "img/str3/funtionalAmbiance.svg",
        "photos": [
            {
                "fileLocation": "img/str3/1.jpg",
                "textDescription": "Brede berm en ligging aan kanaal"
            },
            {
                "fileLocation": "img/str3/2.jpg",
                "textDescription": "Materiaal van parkeerplekken is combinatie van groen en verharding"
            },
            {
                "fileLocation": "img/str3/3.jpg",
                "textDescription": "Redelijk smal voetpad"
            },
            {
                "fileLocation": "img/str3/4.jpg",
                "textDescription": "Afstemming van materialen"
            },
            {
                "fileLocation": "img/str3/5.jpg",
                "textDescription": "Tot 2013"
            },
            {
                "fileLocation": "img/str3/6.jpg",
                "textDescription": "Vanaf 2013"
            }
        ]
    }
]